imbutil/__init__.py
imbutil/_version.py
imbutil/combine/__init__.py
imbutil/combine/minmaxrandom.py
imbutil-0.0.8.dist-info/METADATA
imbutil-0.0.8.dist-info/RECORD
imbutil-0.0.8.dist-info/WHEEL
imbutil-0.0.8.dist-info/top_level.txt
tests/__init__.py
tests/combine/__init__.py
tests/combine/test_minmaxrandom.py
