Metadata-Version: 2.1
Name: imbutil
Version: 0.0.8
Summary: Additions to the imblearn package
Home-page: https://github.com/shaypal5/imbutil
Author: Shay Palachy
Author-email: shay.palachy@gmail.com
License: UNKNOWN
Platform: UNKNOWN
Classifier: Development Status :: 4 - Beta
Classifier: License :: OSI Approved :: MIT License
Classifier: Programming Language :: Python
Classifier: Programming Language :: Python :: 3.5
Classifier: Programming Language :: Python :: 3.6
Classifier: Programming Language :: Python :: 3.7
Classifier: Topic :: Software Development :: Libraries
Classifier: Topic :: Software Development :: Libraries :: Python Modules
Classifier: Intended Audience :: Developers
Provides-Extra: test
Requires-Dist: imbalanced-learn (>=0.3.3)
Provides-Extra: test
Requires-Dist: pytest; extra == 'test'
Requires-Dist: coverage; extra == 'test'
Requires-Dist: pytest-cov; extra == 'test'
Requires-Dist: pandas; extra == 'test'
Requires-Dist: pdutil; extra == 'test'
Requires-Dist: scikit-learn; extra == 'test'
Requires-Dist: collective.checkdocs; extra == 'test'
Requires-Dist: pygments; extra == 'test'
Requires-Dist: imbalanced-learn (>=0.3.3); extra == 'test'
